solve/__init__.py
solve/version.py
solve-0.0.0.dist-info/METADATA
solve-0.0.0.dist-info/WHEEL
solve-0.0.0.dist-info/top_level.txt
solve-0.0.0.dist-info/RECORD
