Metadata-Version: 2.1
Name: solve
Version: 0.0.0
Summary: solve
Home-page: http://pypi.org/project/solve
License: UNKNOWN
Platform: UNKNOWN
Classifier: Programming Language :: Python
Classifier: Intended Audience :: Science/Research
